docs/__init__.py
docs/conf.py
pyCSM/__init__.py
pyCSM/authorization/__init__.py
pyCSM/authorization/auth.py
pyCSM/clients/__init__.py
pyCSM/clients/hardware_client.py
pyCSM/clients/session_client.py
pyCSM/clients/system_client.py
pyCSM/services/__init__.py
pyCSM/services/hardware_service/__init__.py
pyCSM/services/hardware_service/hardware_service.py
pyCSM/services/session_service/__init__.py
pyCSM/services/session_service/copyset_service.py
pyCSM/services/session_service/schedule_service.py
pyCSM/services/session_service/session_service.py
pyCSM/services/system_service/__init__.py
pyCSM/services/system_service/system_service.py
pyCSM/util/__init__.py
pyCSM/util/utility.py
pyCSM-1.0.7.dist-info/LICENSE
pyCSM-1.0.7.dist-info/METADATA
pyCSM-1.0.7.dist-info/WHEEL
pyCSM-1.0.7.dist-info/top_level.txt
pyCSM-1.0.7.dist-info/RECORD
